LICENSE
README.rst
setup.cfg
setup.py
clickhouse_sqlalchemy/__init__.py
clickhouse_sqlalchemy/exceptions.py
clickhouse_sqlalchemy.egg-info/PKG-INFO
clickhouse_sqlalchemy.egg-info/SOURCES.txt
clickhouse_sqlalchemy.egg-info/dependency_links.txt
clickhouse_sqlalchemy.egg-info/entry_points.txt
clickhouse_sqlalchemy.egg-info/requires.txt
clickhouse_sqlalchemy.egg-info/top_level.txt
clickhouse_sqlalchemy/alembic/__init__.py
clickhouse_sqlalchemy/alembic/comparators.py
clickhouse_sqlalchemy/alembic/dialect.py
clickhouse_sqlalchemy/alembic/operations.py
clickhouse_sqlalchemy/alembic/renderers.py
clickhouse_sqlalchemy/alembic/toimpl.py
clickhouse_sqlalchemy/drivers/__init__.py
clickhouse_sqlalchemy/drivers/base.py
clickhouse_sqlalchemy/drivers/reflection.py
clickhouse_sqlalchemy/drivers/asynch/__init__.py
clickhouse_sqlalchemy/drivers/asynch/base.py
clickhouse_sqlalchemy/drivers/asynch/connector.py
clickhouse_sqlalchemy/drivers/compilers/__init__.py
clickhouse_sqlalchemy/drivers/compilers/ddlcompiler.py
clickhouse_sqlalchemy/drivers/compilers/sqlcompiler.py
clickhouse_sqlalchemy/drivers/compilers/typecompiler.py
clickhouse_sqlalchemy/drivers/http/__init__.py
clickhouse_sqlalchemy/drivers/http/base.py
clickhouse_sqlalchemy/drivers/http/connector.py
clickhouse_sqlalchemy/drivers/http/escaper.py
clickhouse_sqlalchemy/drivers/http/exceptions.py
clickhouse_sqlalchemy/drivers/http/transport.py
clickhouse_sqlalchemy/drivers/http/utils.py
clickhouse_sqlalchemy/drivers/native/__init__.py
clickhouse_sqlalchemy/drivers/native/base.py
clickhouse_sqlalchemy/drivers/native/connector.py
clickhouse_sqlalchemy/engines/__init__.py
clickhouse_sqlalchemy/engines/base.py
clickhouse_sqlalchemy/engines/mergetree.py
clickhouse_sqlalchemy/engines/misc.py
clickhouse_sqlalchemy/engines/replicated.py
clickhouse_sqlalchemy/engines/util.py
clickhouse_sqlalchemy/ext/__init__.py
clickhouse_sqlalchemy/ext/clauses.py
clickhouse_sqlalchemy/ext/declarative.py
clickhouse_sqlalchemy/orm/__init__.py
clickhouse_sqlalchemy/orm/query.py
clickhouse_sqlalchemy/orm/session.py
clickhouse_sqlalchemy/sql/__init__.py
clickhouse_sqlalchemy/sql/ddl.py
clickhouse_sqlalchemy/sql/schema.py
clickhouse_sqlalchemy/sql/selectable.py
clickhouse_sqlalchemy/types/__init__.py
