Metadata-Version: 1.2
Name: clickhouse-sqlalchemy
Version: 0.2.4
Summary: Simple ClickHouse SQLAlchemy Dialect
Home-page: https://github.com/xzkostyan/clickhouse-sqlalchemy
Author: Konstantin Lebedev
Author-email: kostyan.lebedev@gmail.com
License: MIT
Project-URL: Documentation, https://clickhouse-sqlalchemy.readthedocs.io
Project-URL: Changes, https://github.com/xzkostyan/clickhouse-sqlalchemy/blob/master/CHANGELOG.md
Keywords: ClickHouse db database cloud analytics
Platform: UNKNOWN
Classifier: Development Status :: 4 - Beta
Classifier: Environment :: Console
Classifier: Intended Audience :: Developers
Classifier: Intended Audience :: Information Technology
Classifier: License :: OSI Approved :: MIT License
Classifier: Operating System :: OS Independent
Classifier: Programming Language :: SQL
Classifier: Programming Language :: Python :: 3
Classifier: Programming Language :: Python :: 3.6
Classifier: Programming Language :: Python :: 3.7
Classifier: Programming Language :: Python :: 3.8
Classifier: Programming Language :: Python :: 3.9
Classifier: Programming Language :: Python :: 3.10
Classifier: Topic :: Database
Classifier: Topic :: Software Development
Classifier: Topic :: Software Development :: Libraries
Classifier: Topic :: Software Development :: Libraries :: Application Frameworks
Classifier: Topic :: Software Development :: Libraries :: Python Modules
Classifier: Topic :: Scientific/Engineering :: Information Analysis
Requires-Python: >=3.7, <4
